Pyro5/__init__.py
Pyro5/api.py
Pyro5/callcontext.py
Pyro5/client.py
Pyro5/configure.py
Pyro5/core.py
Pyro5/errors.py
Pyro5/nameserver.py
Pyro5/nsc.py
Pyro5/protocol.py
Pyro5/serializers.py
Pyro5/server.py
Pyro5/socketutil.py
Pyro5/svr_existingconn.py
Pyro5/svr_multiplex.py
Pyro5/svr_threads.py
Pyro5/compatibility/Pyro4.py
Pyro5/compatibility/__init__.py
Pyro5/utils/__init__.py
Pyro5/utils/echoserver.py
Pyro5/utils/httpgateway.py
Pyro5-5.15.dist-info/LICENSE
Pyro5-5.15.dist-info/METADATA
Pyro5-5.15.dist-info/WHEEL
Pyro5-5.15.dist-info/entry_points.txt
Pyro5-5.15.dist-info/top_level.txt
Pyro5-5.15.dist-info/zip-safe
Pyro5-5.15.dist-info/RECORD
