Metadata-Version: 2.1
Name: Pyro5
Version: 5.15
Summary: Remote object communication library, fifth major version
Home-page: https://github.com/irmen/Pyro5
Author: Irmen de Jong
Author-email: irmen@razorvine.net
License: MIT
Keywords: distributed objects,RPC,remote method call,IPC
Platform: UNKNOWN
Classifier: Development Status :: 5 - Production/Stable
Classifier: Intended Audience :: Developers
Classifier: License :: OSI Approved :: MIT License
Classifier: Natural Language :: English
Classifier: Natural Language :: Dutch
Classifier: Operating System :: OS Independent
Classifier: Programming Language :: Python
Classifier: Programming Language :: Python :: 3
Classifier: Topic :: Software Development :: Object Brokering
Classifier: Topic :: System :: Distributed Computing
Classifier: Topic :: System :: Networking
Requires-Python: >=3.7
License-File: LICENSE
